Metadata-Version: 1.1
Name: sed-eval
Version: 0.2.1
Summary: Evaluation toolbox for Sound Event Detection
Home-page: https://github.com/TUT-ARG/sed_eval
Author: Toni Heittola
Author-email: toni.heittola@gmail.com
License: MIT
Keywords: audio analysis,sound event detection,dsp
Platform: UNKNOWN
Classifier: License :: OSI Approved :: MIT License
Classifier: Programming Language :: Python
Classifier: Development Status :: 5 - Production/Stable
Classifier: Intended Audience :: Developers
Classifier: Topic :: Multimedia :: Sound/Audio :: Analysis
Classifier: Programming Language :: Python :: 2.7
